Metadata-Version: 1.1
Name: djangosaml2-tenant
Version: 0.22.0
Summary: pysaml2 integration for multi-tenant in Django
Home-page: https://github.com/advisory/djangosaml2_tenant
Author: Education Advisory Board
Author-email: msensenbrenn@eab.com
License: Apache 2.0
Keywords: django,pysaml2,saml2,federated authentication,multi-tenant
Platform: UNKNOWN
Classifier: Development Status :: 3 - Alpha
Classifier: Environment :: Web Environment
Classifier: Intended Audience :: Developers
Classifier: Operating System :: OS Independent
Classifier: Programming Language :: Python
Classifier: Topic :: Internet :: WWW/HTTP
Classifier: Topic :: Internet :: WWW/HTTP :: WSGI
Classifier: Topic :: Security
Classifier: Topic :: Software Development :: Libraries :: Application Frameworks
